__init__.py
mseep_overseerr_mcp-0.1.5.dist-info/licenses/LICENSE
overseerr_mcp/__init__.py
overseerr_mcp/overseerr.py
overseerr_mcp/server.py
overseerr_mcp/tools.py
mseep_overseerr_mcp-0.1.5.dist-info/METADATA
mseep_overseerr_mcp-0.1.5.dist-info/WHEEL
mseep_overseerr_mcp-0.1.5.dist-info/entry_points.txt
mseep_overseerr_mcp-0.1.5.dist-info/top_level.txt
mseep_overseerr_mcp-0.1.5.dist-info/RECORD
